micro_whois/__init__.py
micro_whois/main.py
micro_whois/response.py
micro_whois-1.1.dist-info/LICENSE
micro_whois-1.1.dist-info/METADATA
micro_whois-1.1.dist-info/WHEEL
micro_whois-1.1.dist-info/top_level.txt
micro_whois-1.1.dist-info/RECORD
