Metadata-Version: 2.1
Name: micro-whois
Version: 1.1
Summary: Cross-platform whois utility in pure Python
Home-page: https://github.com/usiqwerty/micro-whois
Author: usiqwerty
Author-email: 
License: MIT License
License-File: LICENSE
